itoolkit/README
itoolkit/__init__.py
itoolkit/db2/__init__.py
itoolkit/db2/idb2call.py
itoolkit/doc/README
itoolkit/errors.py
itoolkit/itoolkit.py
itoolkit/lib/__init__.py
itoolkit/lib/ilibcall.py
itoolkit/rest/__init__.py
itoolkit/rest/irestcall.py
itoolkit/transport/__init__.py
itoolkit/transport/_direct.py
itoolkit/transport/base.py
itoolkit/transport/database.py
itoolkit/transport/direct.py
itoolkit/transport/http.py
itoolkit/transport/ssh.py
itoolkit-1.7.2.dist-info/METADATA
itoolkit-1.7.2.dist-info/WHEEL
itoolkit-1.7.2.dist-info/LICENSE
itoolkit-1.7.2.dist-info/RECORD
