Metadata-Version: 2.1
Name: itoolkit
Version: 1.7.2
Summary: IBM i XMLSERVICE toolkit for Python
Home-page: https://github.com/IBM/python-itoolkit
License: MIT
Author: Kevin Adler
Author-email: kadler@us.ibm.com
Requires-Python: >=2.7, !=3.0.*, !=3.1.*, !=3.2.*, !=3.3.*
Classifier: Development Status :: 5 - Production/Stable
Classifier: Intended Audience :: Developers
Classifier: License :: OSI Approved :: MIT License
Classifier: Programming Language :: Python :: 2
Classifier: Programming Language :: Python :: 2.7
Classifier: Programming Language :: Python :: 3
Classifier: Programming Language :: Python :: 3.4
Classifier: Programming Language :: Python :: 3.5
Classifier: Programming Language :: Python :: 3.6
Classifier: Programming Language :: Python :: 3.7
Classifier: Programming Language :: Python :: 3.8
Classifier: Programming Language :: Python :: 3.9
Classifier: Programming Language :: Python :: 3.10
Classifier: Programming Language :: Python :: 3.11
Classifier: Topic :: Software Development :: Libraries :: Python Modules
Classifier: Topic :: System
Project-URL: Documentation, https://python-itoolkit.readthedocs.io
Project-URL: Repository, https://github.com/IBM/python-itoolkit
